lichenpy-0.1.6.dist-info/METADATA
lichenpy-0.1.6.dist-info/WHEEL
lichenpy/__init__.py
lichenpy/__init__.pyi
lichenpy/py.typed
lichenpy/lichenpy.cpython-310-arm-linux-gnueabihf.so
lichenpy-0.1.6.dist-info/RECORD
