Metadata-Version: 2.3
Name: lichenpy
Version: 0.1.6
Classifier: Programming Language :: Rust
Classifier: Programming Language :: Python :: Implementation :: CPython
Classifier: Programming Language :: Python :: Implementation :: PyPy
Summary: Fast link extraction from HTML documents
License: MIT
Requires-Python: >=3.7
Project-URL: Source Code, https://github.com/kevinhu/lichen
